sim_sensors/__init__.py
sim_sensors/gas_sensor.py
sim_sensors/humidity_sensor.py
sim_sensors/light_sensor.py
sim_sensors/ph_sensor.py
sim_sensors/pressure_sensor.py
sim_sensors/soil_sensor.py
sim_sensors/temp_sensor.py
sim_sensors/uv_sensor.py
sim_sensors-0.4.1.dist-info/LICENSE.txt
sim_sensors-0.4.1.dist-info/METADATA
sim_sensors-0.4.1.dist-info/WHEEL
sim_sensors-0.4.1.dist-info/top_level.txt
sim_sensors-0.4.1.dist-info/RECORD
