Metadata-Version: 2.1
Name: sim-sensors
Version: 0.4.1
Summary: A collection of classes that simulate IoT sensors
Author-email: Ivan Šarić <ivan@path-variable.com>, BlasePanda <58369256+BlasePanda@users.noreply.github.com>
Project-URL: Homepage, https://github.com/isaric/sim_sensors
Keywords: simulated,sensors,iot
Classifier: License :: OSI Approved :: MIT License
Classifier: Programming Language :: Python
Classifier: Programming Language :: Python :: 3
Classifier: Programming Language :: Python :: 3.10
Requires-Python: >=3.9
License-File: LICENSE.txt
Provides-Extra: dev
Requires-Dist: black ; extra == 'dev'
